xblockutils/__init__.py
xblockutils/base_test.py
xblockutils/helpers.py
xblockutils/publish_event.py
xblockutils/resources.py
xblockutils/settings.py
xblockutils/studio_editable.py
xblockutils/studio_editable_test.py
xblockutils/deprecation/__init__.py
xblockutils/deprecation/warn.py
xblockutils/public/studio_container.js
xblockutils/public/studio_edit.js
xblockutils/templates/add_buttons.html
xblockutils/templates/default_preview_view.html
xblockutils/templates/studio_edit.html
xblockutils/templatetags/__init__.py
xblockutils/templatetags/i18n.py
xblock_utils-4.0.0.dist-info/LICENSE
xblock_utils-4.0.0.dist-info/METADATA
xblock_utils-4.0.0.dist-info/WHEEL
xblock_utils-4.0.0.dist-info/top_level.txt
xblock_utils-4.0.0.dist-info/RECORD
