Metadata-Version: 2.1
Name: xblock-utils
Version: 4.0.0
Summary: Various utilities for XBlocks
Home-page: https://github.com/openedx/xblock-utils
Author: edX
Author-email: oscm@edx.org
License: UNKNOWN
Platform: UNKNOWN
Classifier: Framework :: Django :: 3.2
Classifier: Framework :: Django :: 4.2
Classifier: Programming Language :: Python
Classifier: Programming Language :: Python :: 3
Classifier: Programming Language :: Python :: 3.8
Classifier: Programming Language :: Python :: Implementation :: CPython
Requires-Dist: Xblock[django]
Requires-Dist: mako
Requires-Dist: simplejson
Requires-Dist: web-fragments
